<Map>
	<NpcList>
		
		<!--  <Npc ID="10002" Layer="depthLevel" Name="么么公主" Ex="545" Ey="384" Cmd="act" Param="selectSay" />-->
		
	</NpcList>
	
	<Triggers>
		<!--
		<Trigger ResName="mermaid_mc" Layer="depthLevel" Ex="450" Ey="148" Cmd="p" Param="MermaidAndPrincePanel" Tips="美人鱼与王子的故事" /> 
		<Trigger ResName="go_271" Layer="topLevel" Ex="540" Ey="440" Cmd="alt_map" Param="271" Tips="骑士训练营" />
		-->
		<Trigger ResName="go_120" Layer="topLevel" Ex="55" Ey="370" Cmd="alt_map" Param="120" Tips="云雾谜桥" />
		<Trigger ResName="cardgamebtn" Layer="controlLevel" Ex="800" Ey="315" Cmd="act" Param="onHit" Tips="进入龙之幻境" />
		<Trigger ResName="goto_map" Layer="controlLevel" Ex="465" Ey="145" Cmd="act" Param="fireAction_select" Tips="进入森林训练场" />
		<Trigger ResName="intro" Layer="depthLevel" Ex="571" Ey="409" Cmd="act" Param="callFire" Tips="唤醒木神"/>	
		<Trigger ResName="pos" Layer="controlLevel" Ex="685" Ey="338" Cmd="act" Param="pos" Tips="敬拜木神"/>		
	</Triggers>
	
	<Talks>
		<!--
		<Talk ID="1" NpcID="10015" Face="正常" Msg="Hi，你好啊。" Option="我很好" Cmd="none" Param="6" AddTaskOption="1" />
		-->
		<Talk ID="2" NpcID="10002" Face="正常" Msg="你好！" Option="领取队服 " Cmd="act" Param="startTask" AddTaskOption="1" />
	</Talks>
</Map>
